qwop_fast-0.1.1.dist-info/METADATA
qwop_fast-0.1.1.dist-info/WHEEL
qwop_fast/__init__.py
qwop_fast/__init__.pyi
qwop_fast/py.typed
qwop_fast/qwop_fast.cpython-37m-aarch64-linux-gnu.so
qwop_fast-0.1.1.dist-info/RECORD
